wikiqa/__init__.py
wikiqa/core.py
wikiqa/llm.py
wikiqa/utils.py
wikiqa-0.1.2.dist-info/licenses/LICENSE
wikiqa-0.1.2.dist-info/METADATA
wikiqa-0.1.2.dist-info/WHEEL
wikiqa-0.1.2.dist-info/top_level.txt
wikiqa-0.1.2.dist-info/RECORD
