Metadata-Version: 2.4
Name: wikiqa
Version: 0.1.2
Summary: A powerful Wikipedia QA system with LLM integration
Home-page: https://github.com/pawan2411/WikiQA
Author: Pawan Kumar Rajpoot
Author-email: pawan.rajpoot2411@gmail.com
License: MIT
Project-URL: Bug Reports, https://github.com/pawan2411/WikiQA/issues
Project-URL: Source, https://github.com/pawan2411/WikiQA
Keywords: wikipedia,qa,llm,nlp,artificial intelligence
Classifier: Development Status :: 3 - Alpha
Classifier: Intended Audience :: Developers
Classifier: Programming Language :: Python :: 3
Classifier: Programming Language :: Python :: 3.8
Classifier: Programming Language :: Python :: 3.9
Classifier: Programming Language :: Python :: 3.10
Classifier: Topic :: Scientific/Engineering :: Artificial Intelligence
Classifier: Topic :: Text Processing :: General
Requires-Python: >=3.8
License-File: LICENSE
Requires-Dist: wikipedia>=1.4.0
Requires-Dist: openai>=1.0.0
Requires-Dist: anthropic>=0.5.0
Requires-Dist: together>=0.1.0
Requires-Dist: spacy>=3.0.0
Requires-Dist: pandas>=2.0.0
Requires-Dist: numpy>=1.20.0
Requires-Dist: python-dateutil>=2.8.2
Requires-Dist: tqdm>=4.65.0
Dynamic: author
Dynamic: author-email
Dynamic: classifier
Dynamic: description
Dynamic: description-content-type
Dynamic: home-page
Dynamic: keywords
Dynamic: license
Dynamic: license-file
Dynamic: project-url
Dynamic: requires-dist
Dynamic: requires-python
Dynamic: summary
